{
    "key": "group_5c79212113db6",
    "title": "Theme Optionen Klon",
    "fields": [
        {
            "key": "field_5c7cd0cec6938",
            "label": "Logo",
            "name": "logo",
            "type": "image",
            "instructions": "Lade Sie hier Ihr Firmenlogo hoch.  Dieses wird in der Navigation und im Footer angezeigt.",
            "required": 0,
            "conditional_logic": 0,
            "wrapper": {
                "width": "",
                "class": "",
                "id": ""
            },
            "return_format": "array",
            "preview_size": "thumbnail",
            "library": "all",
            "min_width": "",
            "min_height": "",
            "min_size": "",
            "max_width": "",
            "max_height": "",
            "max_size": "",
            "mime_types": ""
        },
        {
            "key": "field_5c862857c64b2",
            "label": "Archivseite News\/Medienmitteilungen",
            "name": "archive_post",
            "type": "page_link",
            "instructions": "Geben Sie an, welche Seite als Übersichtsseite für die Beiträge verwendet wird.",
            "required": 0,
            "conditional_logic": 0,
            "wrapper": {
                "width": "",
                "class": "",
                "id": ""
            },
            "post_type": [
                "page"
            ],
            "taxonomy": "",
            "allow_null": 1,
            "allow_archives": 1,
            "multiple": 0
        },
        {
            "key": "field_5d1a0532e401a",
            "label": "Footer Adresse",
            "name": "address",
            "type": "wysiwyg",
            "instructions": "",
            "required": 0,
            "conditional_logic": 0,
            "wrapper": {
                "width": "",
                "class": "",
                "id": ""
            },
            "default_value": "",
            "tabs": "all",
            "toolbar": "full",
            "media_upload": 1,
            "delay": 0
        }
    ],
    "location": [
        [
            {
                "param": "options_page",
                "operator": "==",
                "value": "theme-options"
            }
        ]
    ],
    "menu_order": 0,
    "position": "normal",
    "style": "default",
    "label_placement": "top",
    "instruction_placement": "label",
    "hide_on_screen": "",
    "active": 0,
    "description": "",
    "modified": 1561986375
}